acoustools/Constants.py
acoustools/Constraints.py
acoustools/Force.py
acoustools/Gorkov.py
acoustools/HandTracking.py
acoustools/Intepreter.py
acoustools/Levitator.py
acoustools/Mesh.py
acoustools/Solvers.py
acoustools/Stiffness.py
acoustools/Visualiser.py
acoustools/__about__.py
acoustools/__init__.py
acoustools/BEM/Force.py
acoustools/BEM/Forward_models.py
acoustools/BEM/Gorkov.py
acoustools/BEM/Propagator.py
acoustools/BEM/Stiffness.py
acoustools/BEM/__init__.py
acoustools/BEM/Gradients/E_Gradient.py
acoustools/BEM/Gradients/H_Gradient.py
acoustools/BEM/Gradients/__init__.py
acoustools/Export/CSV.py
acoustools/Export/Holo.py
acoustools/Export/Pickle.py
acoustools/Export/__init__.py
acoustools/Export/lcode.py
acoustools/Fabrication/Optimise.py
acoustools/Fabrication/Translator.py
acoustools/Fabrication/__init__.py
acoustools/Optimise/Constraints.py
acoustools/Optimise/Objectives.py
acoustools/Optimise/__init__.py
acoustools/Paths/Bezier.py
acoustools/Paths/Curves.py
acoustools/Paths/Distances.py
acoustools/Paths/Interpolate.py
acoustools/Paths/Numerals.py
acoustools/Paths/__init__.py
acoustools/Utilities/Boards.py
acoustools/Utilities/Forward_models.py
acoustools/Utilities/Piston_model_gradients.py
acoustools/Utilities/Points.py
acoustools/Utilities/Propagators.py
acoustools/Utilities/Setup.py
acoustools/Utilities/Signatures.py
acoustools/Utilities/Targets.py
acoustools/Utilities/Utilities.py
acoustools/Utilities/__init__.py
acoustools-1.0.5.dist-info/METADATA
acoustools-1.0.5.dist-info/WHEEL
acoustools-1.0.5.dist-info/RECORD
