Metadata-Version: 2.4
Name: acoustools
Version: 1.0.5
Summary: A Full-Stack Python based library for working with acoustic fields for holgraphy
Project-URL: Documentation, https://joshuamukherjee.github.io/AcousTools/src/acoustools.html
Project-URL: Issues, https://github.com/JoshuaMukherjee/AcousTools
Project-URL: Source, https://github.com/JoshuaMukherjee/AcousTools
Author-email: JoshuaMukherjee <joshuaakmukherjee@gmail.com>
License-Expression: MIT
Classifier: Development Status :: 4 - Beta
Classifier: Programming Language :: Python
Classifier: Programming Language :: Python :: 3.7
Classifier: Programming Language :: Python :: 3.8
Classifier: Programming Language :: Python :: 3.9
Classifier: Programming Language :: Python :: 3.10
Classifier: Programming Language :: Python :: 3.11
Classifier: Programming Language :: Python :: Implementation :: CPython
Classifier: Programming Language :: Python :: Implementation :: PyPy
Requires-Python: >=3.7
